LICENSE
MANIFEST.in
README.md
setup.py
devsafe/__init__.py
devsafe/tests.py
devsafe/management/__init__.py
devsafe/management/commands/__init__.py
devsafe/management/commands/devsafe.py
django_devsafe.egg-info/PKG-INFO
django_devsafe.egg-info/SOURCES.txt
django_devsafe.egg-info/dependency_links.txt
django_devsafe.egg-info/top_level.txt